CHANGES.txt
README.txt
buildout.cfg
setup.py
src/bud/__init__.py
src/bud.nospam.egg-info/PKG-INFO
src/bud.nospam.egg-info/SOURCES.txt
src/bud.nospam.egg-info/dependency_links.txt
src/bud.nospam.egg-info/namespace_packages.txt
src/bud.nospam.egg-info/not-zip-safe
src/bud.nospam.egg-info/requires.txt
src/bud.nospam.egg-info/top_level.txt
src/bud/nospam/__init__.py
src/bud/nospam/tests.py