Metadata-Version: 1.0
Name: bud.nospam
Version: 1.0.1
Summary: ROT 13 encrypt text to prevent spam
Home-page: UNKNOWN
Author: Kevin Teague
Author-email: kevin@bud.ca
License: BSD
Keywords: web spam
Platform: UNKNOWN
Classifier: Programming Language :: Python
Classifier: Topic :: Software Development :: Libraries :: Python Modules
Classifier: Topic :: Text Processing :: Markup :: HTML
